batchypegger.py
batchypegger-0.5.4.dist-info/LICENSE
batchypegger-0.5.4.dist-info/METADATA
batchypegger-0.5.4.dist-info/WHEEL
batchypegger-0.5.4.dist-info/entry_points.txt
batchypegger-0.5.4.dist-info/top_level.txt
batchypegger-0.5.4.dist-info/RECORD
