Metadata-Version: 2.1
Name: batchypegger
Version: 0.5.4
Summary: apply ffmpeg in a batchy way
Home-page: https://github.com/sofakid/batchypegger
Author: Lucas
Author-email: lucas@example.com
License: MIT
Platform: UNKNOWN
Classifier: Programming Language :: Python :: 3.7
Classifier: Operating System :: OS Independent
Requires-Python: >=3.7
